{
	"type": "Program",
	"start": 0,
	"end": 2015,
	"body": [
		{
			"type": "ClassDeclaration",
			"start": 0,
			"end": 1953,
			"id": {
				"type": "Identifier",
				"start": 6,
				"end": 9,
				"name": "MQ5"
			},
			"superClass": null,
			"body": {
				"type": "ClassBody",
				"start": 10,
				"end": 1953,
				"body": [
					{
						"type": "MethodDefinition",
						"start": 103,
						"end": 399,
						"kind": "constructor",
						"static": false,
						"computed": false,
						"key": {
							"type": "Identifier",
							"start": 103,
							"end": 114,
							"name": "constructor"
						},
						"value": {
							"type": "FunctionExpression",
							"start": 114,
							"end": 399,
							"id": null,
							"expression": false,
							"generator": false,
							"async": false,
							"params": [],
							"body": {
								"type": "BlockStatement",
								"start": 117,
								"end": 399,
								"body": [
									{
										"type": "ExpressionStatement",
										"start": 123,
										"end": 162,
										"expression": {
											"type": "AssignmentExpression",
											"start": 123,
											"end": 161,
											"operator": "=",
											"left": {
												"type": "MemberExpression",
												"start": 123,
												"end": 132,
												"object": {
													"type": "ThisExpression",
													"start": 123,
													"end": 127
												},
												"property": {
													"type": "Identifier",
													"start": 128,
													"end": 132,
													"name": "keys"
												},
												"computed": false
											},
											"right": {
												"type": "ArrayExpression",
												"start": 135,
												"end": 161,
												"elements": [
													{
														"type": "Literal",
														"start": 136,
														"end": 141,
														"value": "gnd",
														"raw": "'gnd'"
													},
													{
														"type": "Literal",
														"start": 143,
														"end": 148,
														"value": "vcc",
														"raw": "'vcc'"
													},
													{
														"type": "Literal",
														"start": 150,
														"end": 154,
														"value": "do",
														"raw": "'do'"
													},
													{
														"type": "Literal",
														"start": 156,
														"end": 160,
														"value": "ao",
														"raw": "'ao'"
													}
												]
											}
										}
									},
									{
										"type": "ExpressionStatement",
										"start": 167,
										"end": 190,
										"expression": {
											"type": "AssignmentExpression",
											"start": 167,
											"end": 189,
											"operator": "=",
											"left": {
												"type": "MemberExpression",
												"start": 167,
												"end": 184,
												"object": {
													"type": "ThisExpression",
													"start": 167,
													"end": 171
												},
												"property": {
													"type": "Identifier",
													"start": 172,
													"end": 184,
													"name": "requiredKeys"
												},
												"computed": false
											},
											"right": {
												"type": "ArrayExpression",
												"start": 187,
												"end": 189,
												"elements": []
											}
										}
									},
									{
										"type": "ExpressionStatement",
										"start": 196,
										"end": 228,
										"expression": {
											"type": "AssignmentExpression",
											"start": 196,
											"end": 227,
											"operator": "=",
											"left": {
												"type": "MemberExpression",
												"start": 196,
												"end": 215,
												"object": {
													"type": "ThisExpression",
													"start": 196,
													"end": 200
												},
												"property": {
													"type": "Identifier",
													"start": 201,
													"end": 215,
													"name": "onchangeanalog"
												},
												"computed": false
											},
											"right": {
												"type": "Identifier",
												"start": 218,
												"end": 227,
												"name": "undefined"
											}
										}
									},
									{
										"type": "ExpressionStatement",
										"start": 233,
										"end": 266,
										"expression": {
											"type": "AssignmentExpression",
											"start": 233,
											"end": 265,
											"operator": "=",
											"left": {
												"type": "MemberExpression",
												"start": 233,
												"end": 253,
												"object": {
													"type": "ThisExpression",
													"start": 233,
													"end": 237
												},
												"property": {
													"type": "Identifier",
													"start": 238,
													"end": 253,
													"name": "onchangedigital"
												},
												"computed": false
											},
											"right": {
												"type": "Identifier",
												"start": 256,
												"end": 265,
												"name": "undefined"
											}
										}
									},
									{
										"type": "ExpressionStatement",
										"start": 271,
										"end": 304,
										"expression": {
											"type": "AssignmentExpression",
											"start": 271,
											"end": 303,
											"operator": "=",
											"left": {
												"type": "MemberExpression",
												"start": 271,
												"end": 291,
												"object": {
													"type": "ThisExpression",
													"start": 271,
													"end": 275
												},
												"property": {
													"type": "Identifier",
													"start": 276,
													"end": 291,
													"name": "onexceedvoltage"
												},
												"computed": false
											},
											"right": {
												"type": "Identifier",
												"start": 294,
												"end": 303,
												"name": "undefined"
											}
										}
									},
									{
										"type": "ExpressionStatement",
										"start": 309,
										"end": 339,
										"expression": {
											"type": "AssignmentExpression",
											"start": 309,
											"end": 338,
											"operator": "=",
											"left": {
												"type": "MemberExpression",
												"start": 309,
												"end": 326,
												"object": {
													"type": "ThisExpression",
													"start": 309,
													"end": 313
												},
												"property": {
													"type": "Identifier",
													"start": 314,
													"end": 326,
													"name": "voltageLimit"
												},
												"computed": false
											},
											"right": {
												"type": "Identifier",
												"start": 329,
												"end": 338,
												"name": "undefined"
											}
										}
									}
								]
							}
						}
					},
					{
						"type": "MethodDefinition",
						"start": 403,
						"end": 461,
						"kind": "method",
						"static": true,
						"computed": false,
						"key": {
							"type": "Identifier",
							"start": 410,
							"end": 414,
							"name": "info"
						},
						"value": {
							"type": "FunctionExpression",
							"start": 414,
							"end": 461,
							"id": null,
							"expression": false,
							"generator": false,
							"async": false,
							"params": [],
							"body": {
								"type": "BlockStatement",
								"start": 417,
								"end": 461,
								"body": [
									{
										"type": "ReturnStatement",
										"start": 423,
										"end": 457,
										"argument": {
											"type": "ObjectExpression",
											"start": 430,
											"end": 456,
											"properties": [
												{
													"type": "Property",
													"start": 438,
													"end": 449,
													"method": false,
													"shorthand": false,
													"computed": false,
													"key": {
														"type": "Identifier",
														"start": 438,
														"end": 442,
														"name": "name"
													},
													"value": {
														"type": "Literal",
														"start": 444,
														"end": 449,
														"value": "MQ5",
														"raw": "'MQ5'"
													},
													"kind": "init"
												}
											]
										}
									}
								]
							}
						}
					},
					{
						"type": "MethodDefinition",
						"start": 465,
						"end": 1332,
						"kind": "method",
						"static": false,
						"computed": false,
						"key": {
							"type": "Identifier",
							"start": 465,
							"end": 470,
							"name": "wired"
						},
						"value": {
							"type": "FunctionExpression",
							"start": 470,
							"end": 1332,
							"id": null,
							"expression": false,
							"generator": false,
							"async": false,
							"params": [
								{
									"type": "Identifier",
									"start": 471,
									"end": 476,
									"name": "obniz"
								}
							],
							"body": {
								"type": "BlockStatement",
								"start": 478,
								"end": 1332,
								"body": [
									{
										"type": "ExpressionStatement",
										"start": 484,
										"end": 503,
										"expression": {
											"type": "AssignmentExpression",
											"start": 484,
											"end": 502,
											"operator": "=",
											"left": {
												"type": "MemberExpression",
												"start": 484,
												"end": 494,
												"object": {
													"type": "ThisExpression",
													"start": 484,
													"end": 488
												},
												"property": {
													"type": "Identifier",
													"start": 489,
													"end": 494,
													"name": "obniz"
												},
												"computed": false
											},
											"right": {
												"type": "Identifier",
												"start": 497,
												"end": 502,
												"name": "obniz"
											}
										}
									},
									{
										"type": "ExpressionStatement",
										"start": 509,
										"end": 536,
										"expression": {
											"type": "AssignmentExpression",
											"start": 509,
											"end": 535,
											"operator": "=",
											"left": {
												"type": "MemberExpression",
												"start": 509,
												"end": 517,
												"object": {
													"type": "ThisExpression",
													"start": 509,
													"end": 513
												},
												"property": {
													"type": "Identifier",
													"start": 514,
													"end": 517,
													"name": "vcc"
												},
												"computed": false
											},
											"right": {
												"type": "MemberExpression",
												"start": 520,
												"end": 535,
												"object": {
													"type": "MemberExpression",
													"start": 520,
													"end": 531,
													"object": {
														"type": "ThisExpression",
														"start": 520,
														"end": 524
													},
													"property": {
														"type": "Identifier",
														"start": 525,
														"end": 531,
														"name": "params"
													},
													"computed": false
												},
												"property": {
													"type": "Identifier",
													"start": 532,
													"end": 535,
													"name": "vcc"
												},
												"computed": false
											}
										}
									},
									{
										"type": "ExpressionStatement",
										"start": 541,
										"end": 568,
										"expression": {
											"type": "AssignmentExpression",
											"start": 541,
											"end": 567,
											"operator": "=",
											"left": {
												"type": "MemberExpression",
												"start": 541,
												"end": 549,
												"object": {
													"type": "ThisExpression",
													"start": 541,
													"end": 545
												},
												"property": {
													"type": "Identifier",
													"start": 546,
													"end": 549,
													"name": "gnd"
												},
												"computed": false
											},
											"right": {
												"type": "MemberExpression",
												"start": 552,
												"end": 567,
												"object": {
													"type": "MemberExpression",
													"start": 552,
													"end": 563,
													"object": {
														"type": "ThisExpression",
														"start": 552,
														"end": 556
													},
													"property": {
														"type": "Identifier",
														"start": 557,
														"end": 563,
														"name": "params"
													},
													"computed": false
												},
												"property": {
													"type": "Identifier",
													"start": 564,
													"end": 567,
													"name": "gnd"
												},
												"computed": false
											}
										}
									},
									{
										"type": "IfStatement",
										"start": 574,
										"end": 1081,
										"test": {
											"type": "CallExpression",
											"start": 578,
											"end": 614,
											"callee": {
												"type": "MemberExpression",
												"start": 578,
												"end": 598,
												"object": {
													"type": "MemberExpression",
													"start": 578,
													"end": 588,
													"object": {
														"type": "ThisExpression",
														"start": 578,
														"end": 582
													},
													"property": {
														"type": "Identifier",
														"start": 583,
														"end": 588,
														"name": "obniz"
													},
													"computed": false
												},
												"property": {
													"type": "Identifier",
													"start": 589,
													"end": 598,
													"name": "isValidIO"
												},
												"computed": false
											},
											"arguments": [
												{
													"type": "MemberExpression",
													"start": 599,
													"end": 613,
													"object": {
														"type": "MemberExpression",
														"start": 599,
														"end": 610,
														"object": {
															"type": "ThisExpression",
															"start": 599,
															"end": 603
														},
														"property": {
															"type": "Identifier",
															"start": 604,
															"end": 610,
															"name": "params"
														},
														"computed": false
													},
													"property": {
														"type": "Identifier",
														"start": 611,
														"end": 613,
														"name": "ao"
													},
													"computed": false
												}
											]
										},
										"consequent": {
											"type": "BlockStatement",
											"start": 616,
											"end": 1081,
											"body": [
												{
													"type": "ExpressionStatement",
													"start": 624,
													"end": 662,
													"expression": {
														"type": "AssignmentExpression",
														"start": 624,
														"end": 661,
														"operator": "=",
														"left": {
															"type": "MemberExpression",
															"start": 624,
															"end": 631,
															"object": {
																"type": "ThisExpression",
																"start": 624,
																"end": 628
															},
															"property": {
																"type": "Identifier",
																"start": 629,
																"end": 631,
																"name": "ad"
															},
															"computed": false
														},
														"right": {
															"type": "CallExpression",
															"start": 634,
															"end": 661,
															"callee": {
																"type": "MemberExpression",
																"start": 634,
																"end": 645,
																"object": {
																	"type": "Identifier",
																	"start": 634,
																	"end": 639,
																	"name": "obniz"
																},
																"property": {
																	"type": "Identifier",
																	"start": 640,
																	"end": 645,
																	"name": "getAD"
																},
																"computed": false
															},
															"arguments": [
																{
																	"type": "MemberExpression",
																	"start": 646,
																	"end": 660,
																	"object": {
																		"type": "MemberExpression",
																		"start": 646,
																		"end": 657,
																		"object": {
																			"type": "ThisExpression",
																			"start": 646,
																			"end": 650
																		},
																		"property": {
																			"type": "Identifier",
																			"start": 651,
																			"end": 657,
																			"name": "params"
																		},
																		"computed": false
																	},
																	"property": {
																		"type": "Identifier",
																		"start": 658,
																		"end": 660,
																		"name": "ao"
																	},
																	"computed": false
																}
															]
														}
													}
												},
												{
													"type": "ExpressionStatement",
													"start": 669,
													"end": 1075,
													"expression": {
														"type": "CallExpression",
														"start": 669,
														"end": 1074,
														"callee": {
															"type": "MemberExpression",
															"start": 669,
															"end": 682,
															"object": {
																"type": "MemberExpression",
																"start": 669,
																"end": 676,
																"object": {
																	"type": "ThisExpression",
																	"start": 669,
																	"end": 673
																},
																"property": {
																	"type": "Identifier",
																	"start": 674,
																	"end": 676,
																	"name": "ad"
																},
																"computed": false
															},
															"property": {
																"type": "Identifier",
																"start": 677,
																"end": 682,
																"name": "start"
															},
															"computed": false
														},
														"arguments": [
															{
																"type": "ArrowFunctionExpression",
																"start": 683,
																"end": 1073,
																"id": null,
																"expression": false,
																"generator": false,
																"async": false,
																"params": [
																	{
																		"type": "Identifier",
																		"start": 683,
																		"end": 690,
																		"name": "voltage"
																	}
																],
																"body": {
																	"type": "BlockStatement",
																	"start": 694,
																	"end": 1073,
																	"body": [
																		{
																			"type": "IfStatement",
																			"start": 748,
																			"end": 845,
																			"test": {
																				"type": "BinaryExpression",
																				"start": 752,
																				"end": 792,
																				"left": {
																					"type": "UnaryExpression",
																					"start": 752,
																					"end": 778,
																					"operator": "typeof",
																					"prefix": true,
																					"argument": {
																						"type": "MemberExpression",
																						"start": 759,
																						"end": 778,
																						"object": {
																							"type": "ThisExpression",
																							"start": 759,
																							"end": 763
																						},
																						"property": {
																							"type": "Identifier",
																							"start": 764,
																							"end": 778,
																							"name": "onchangeanalog"
																						},
																						"computed": false
																					}
																				},
																				"operator": "==",
																				"right": {
																					"type": "Literal",
																					"start": 782,
																					"end": 792,
																					"value": "function",
																					"raw": "'function'"
																				}
																			},
																			"consequent": {
																				"type": "BlockStatement",
																				"start": 794,
																				"end": 845,
																				"body": [
																					{
																						"type": "ExpressionStatement",
																						"start": 806,
																						"end": 835,
																						"expression": {
																							"type": "CallExpression",
																							"start": 806,
																							"end": 834,
																							"callee": {
																								"type": "MemberExpression",
																								"start": 806,
																								"end": 825,
																								"object": {
																									"type": "ThisExpression",
																									"start": 806,
																									"end": 810
																								},
																								"property": {
																									"type": "Identifier",
																									"start": 811,
																									"end": 825,
																									"name": "onchangeanalog"
																								},
																								"computed": false
																							},
																							"arguments": [
																								{
																									"type": "Identifier",
																									"start": 826,
																									"end": 833,
																									"name": "voltage"
																								}
																							]
																						}
																					}
																				]
																			},
																			"alternate": null
																		},
																		{
																			"type": "IfStatement",
																			"start": 854,
																			"end": 1065,
																			"test": {
																				"type": "LogicalExpression",
																				"start": 869,
																				"end": 1002,
																				"left": {
																					"type": "LogicalExpression",
																					"start": 869,
																					"end": 947,
																					"left": {
																						"type": "BinaryExpression",
																						"start": 869,
																						"end": 905,
																						"left": {
																							"type": "UnaryExpression",
																							"start": 869,
																							"end": 893,
																							"operator": "typeof",
																							"prefix": true,
																							"argument": {
																								"type": "MemberExpression",
																								"start": 876,
																								"end": 893,
																								"object": {
																									"type": "ThisExpression",
																									"start": 876,
																									"end": 880
																								},
																								"property": {
																									"type": "Identifier",
																									"start": 881,
																									"end": 893,
																									"name": "voltageLimit"
																								},
																								"computed": false
																							}
																						},
																						"operator": "==",
																						"right": {
																							"type": "Literal",
																							"start": 897,
																							"end": 905,
																							"value": "number",
																							"raw": "'number'"
																						}
																					},
																					"operator": "&&",
																					"right": {
																						"type": "BinaryExpression",
																						"start": 919,
																						"end": 947,
																						"left": {
																							"type": "MemberExpression",
																							"start": 919,
																							"end": 936,
																							"object": {
																								"type": "ThisExpression",
																								"start": 919,
																								"end": 923
																							},
																							"property": {
																								"type": "Identifier",
																								"start": 924,
																								"end": 936,
																								"name": "voltageLimit"
																							},
																							"computed": false
																						},
																						"operator": "<=",
																						"right": {
																							"type": "Identifier",
																							"start": 940,
																							"end": 947,
																							"name": "voltage"
																						}
																					}
																				},
																				"operator": "&&",
																				"right": {
																					"type": "BinaryExpression",
																					"start": 961,
																					"end": 1002,
																					"left": {
																						"type": "UnaryExpression",
																						"start": 961,
																						"end": 988,
																						"operator": "typeof",
																						"prefix": true,
																						"argument": {
																							"type": "MemberExpression",
																							"start": 968,
																							"end": 988,
																							"object": {
																								"type": "ThisExpression",
																								"start": 968,
																								"end": 972
																							},
																							"property": {
																								"type": "Identifier",
																								"start": 973,
																								"end": 988,
																								"name": "onexceedvoltage"
																							},
																							"computed": false
																						}
																					},
																					"operator": "==",
																					"right": {
																						"type": "Literal",
																						"start": 992,
																						"end": 1002,
																						"value": "function",
																						"raw": "'function'"
																					}
																				}
																			},
																			"consequent": {
																				"type": "BlockStatement",
																				"start": 1013,
																				"end": 1065,
																				"body": [
																					{
																						"type": "ExpressionStatement",
																						"start": 1025,
																						"end": 1055,
																						"expression": {
																							"type": "CallExpression",
																							"start": 1025,
																							"end": 1054,
																							"callee": {
																								"type": "MemberExpression",
																								"start": 1025,
																								"end": 1045,
																								"object": {
																									"type": "ThisExpression",
																									"start": 1025,
																									"end": 1029
																								},
																								"property": {
																									"type": "Identifier",
																									"start": 1030,
																									"end": 1045,
																									"name": "onexceedvoltage"
																								},
																								"computed": false
																							},
																							"arguments": [
																								{
																									"type": "Identifier",
																									"start": 1046,
																									"end": 1053,
																									"name": "voltage"
																								}
																							]
																						}
																					}
																				]
																			},
																			"alternate": null
																		}
																	]
																}
															}
														]
													}
												}
											]
										},
										"alternate": null
									},
									{
										"type": "IfStatement",
										"start": 1087,
										"end": 1328,
										"test": {
											"type": "CallExpression",
											"start": 1091,
											"end": 1127,
											"callee": {
												"type": "MemberExpression",
												"start": 1091,
												"end": 1111,
												"object": {
													"type": "MemberExpression",
													"start": 1091,
													"end": 1101,
													"object": {
														"type": "ThisExpression",
														"start": 1091,
														"end": 1095
													},
													"property": {
														"type": "Identifier",
														"start": 1096,
														"end": 1101,
														"name": "obniz"
													},
													"computed": false
												},
												"property": {
													"type": "Identifier",
													"start": 1102,
													"end": 1111,
													"name": "isValidIO"
												},
												"computed": false
											},
											"arguments": [
												{
													"type": "MemberExpression",
													"start": 1112,
													"end": 1126,
													"object": {
														"type": "MemberExpression",
														"start": 1112,
														"end": 1123,
														"object": {
															"type": "ThisExpression",
															"start": 1112,
															"end": 1116
														},
														"property": {
															"type": "Identifier",
															"start": 1117,
															"end": 1123,
															"name": "params"
														},
														"computed": false
													},
													"property": {
														"type": "Identifier",
														"start": 1124,
														"end": 1126,
														"name": "do"
													},
													"computed": false
												}
											]
										},
										"consequent": {
											"type": "BlockStatement",
											"start": 1129,
											"end": 1328,
											"body": [
												{
													"type": "ExpressionStatement",
													"start": 1137,
													"end": 1175,
													"expression": {
														"type": "AssignmentExpression",
														"start": 1137,
														"end": 1174,
														"operator": "=",
														"left": {
															"type": "MemberExpression",
															"start": 1137,
															"end": 1144,
															"object": {
																"type": "ThisExpression",
																"start": 1137,
																"end": 1141
															},
															"property": {
																"type": "Identifier",
																"start": 1142,
																"end": 1144,
																"name": "do"
															},
															"computed": false
														},
														"right": {
															"type": "CallExpression",
															"start": 1147,
															"end": 1174,
															"callee": {
																"type": "MemberExpression",
																"start": 1147,
																"end": 1158,
																"object": {
																	"type": "Identifier",
																	"start": 1147,
																	"end": 1152,
																	"name": "obniz"
																},
																"property": {
																	"type": "Identifier",
																	"start": 1153,
																	"end": 1158,
																	"name": "getIO"
																},
																"computed": false
															},
															"arguments": [
																{
																	"type": "MemberExpression",
																	"start": 1159,
																	"end": 1173,
																	"object": {
																		"type": "MemberExpression",
																		"start": 1159,
																		"end": 1170,
																		"object": {
																			"type": "ThisExpression",
																			"start": 1159,
																			"end": 1163
																		},
																		"property": {
																			"type": "Identifier",
																			"start": 1164,
																			"end": 1170,
																			"name": "params"
																		},
																		"computed": false
																	},
																	"property": {
																		"type": "Identifier",
																		"start": 1171,
																		"end": 1173,
																		"name": "do"
																	},
																	"computed": false
																}
															]
														}
													}
												},
												{
													"type": "ExpressionStatement",
													"start": 1182,
													"end": 1322,
													"expression": {
														"type": "CallExpression",
														"start": 1182,
														"end": 1321,
														"callee": {
															"type": "MemberExpression",
															"start": 1182,
															"end": 1195,
															"object": {
																"type": "MemberExpression",
																"start": 1182,
																"end": 1189,
																"object": {
																	"type": "ThisExpression",
																	"start": 1182,
																	"end": 1186
																},
																"property": {
																	"type": "Identifier",
																	"start": 1187,
																	"end": 1189,
																	"name": "do"
																},
																"computed": false
															},
															"property": {
																"type": "Identifier",
																"start": 1190,
																"end": 1195,
																"name": "input"
															},
															"computed": false
														},
														"arguments": [
															{
																"type": "ArrowFunctionExpression",
																"start": 1196,
																"end": 1320,
																"id": null,
																"expression": false,
																"generator": false,
																"async": false,
																"params": [
																	{
																		"type": "Identifier",
																		"start": 1196,
																		"end": 1201,
																		"name": "value"
																	}
																],
																"body": {
																	"type": "BlockStatement",
																	"start": 1205,
																	"end": 1320,
																	"body": [
																		{
																			"type": "IfStatement",
																			"start": 1215,
																			"end": 1312,
																			"test": {
																				"type": "BinaryExpression",
																				"start": 1219,
																				"end": 1260,
																				"left": {
																					"type": "UnaryExpression",
																					"start": 1219,
																					"end": 1246,
																					"operator": "typeof",
																					"prefix": true,
																					"argument": {
																						"type": "MemberExpression",
																						"start": 1226,
																						"end": 1246,
																						"object": {
																							"type": "ThisExpression",
																							"start": 1226,
																							"end": 1230
																						},
																						"property": {
																							"type": "Identifier",
																							"start": 1231,
																							"end": 1246,
																							"name": "onchangedigital"
																						},
																						"computed": false
																					}
																				},
																				"operator": "==",
																				"right": {
																					"type": "Literal",
																					"start": 1250,
																					"end": 1260,
																					"value": "function",
																					"raw": "'function'"
																				}
																			},
																			"consequent": {
																				"type": "BlockStatement",
																				"start": 1262,
																				"end": 1312,
																				"body": [
																					{
																						"type": "ExpressionStatement",
																						"start": 1274,
																						"end": 1302,
																						"expression": {
																							"type": "CallExpression",
																							"start": 1274,
																							"end": 1301,
																							"callee": {
																								"type": "MemberExpression",
																								"start": 1274,
																								"end": 1294,
																								"object": {
																									"type": "ThisExpression",
																									"start": 1274,
																									"end": 1278
																								},
																								"property": {
																									"type": "Identifier",
																									"start": 1279,
																									"end": 1294,
																									"name": "onchangedigital"
																								},
																								"computed": false
																							},
																							"arguments": [
																								{
																									"type": "Identifier",
																									"start": 1295,
																									"end": 1300,
																									"name": "value"
																								}
																							]
																						}
																					}
																				]
																			},
																			"alternate": null
																		}
																	]
																}
															}
														]
													}
												}
											]
										},
										"alternate": null
									}
								]
							}
						}
					},
					{
						"type": "MethodDefinition",
						"start": 1336,
						"end": 1408,
						"kind": "method",
						"static": false,
						"computed": false,
						"key": {
							"type": "Identifier",
							"start": 1336,
							"end": 1348,
							"name": "startHeating"
						},
						"value": {
							"type": "FunctionExpression",
							"start": 1348,
							"end": 1408,
							"id": null,
							"expression": false,
							"generator": false,
							"async": false,
							"params": [],
							"body": {
								"type": "BlockStatement",
								"start": 1351,
								"end": 1408,
								"body": [
									{
										"type": "ExpressionStatement",
										"start": 1357,
										"end": 1404,
										"expression": {
											"type": "CallExpression",
											"start": 1357,
											"end": 1403,
											"callee": {
												"type": "MemberExpression",
												"start": 1357,
												"end": 1377,
												"object": {
													"type": "MemberExpression",
													"start": 1357,
													"end": 1367,
													"object": {
														"type": "ThisExpression",
														"start": 1357,
														"end": 1361
													},
													"property": {
														"type": "Identifier",
														"start": 1362,
														"end": 1367,
														"name": "obniz"
													},
													"computed": false
												},
												"property": {
													"type": "Identifier",
													"start": 1368,
													"end": 1377,
													"name": "setVccGnd"
												},
												"computed": false
											},
											"arguments": [
												{
													"type": "MemberExpression",
													"start": 1378,
													"end": 1386,
													"object": {
														"type": "ThisExpression",
														"start": 1378,
														"end": 1382
													},
													"property": {
														"type": "Identifier",
														"start": 1383,
														"end": 1386,
														"name": "vcc"
													},
													"computed": false
												},
												{
													"type": "MemberExpression",
													"start": 1388,
													"end": 1396,
													"object": {
														"type": "ThisExpression",
														"start": 1388,
														"end": 1392
													},
													"property": {
														"type": "Identifier",
														"start": 1393,
														"end": 1396,
														"name": "gnd"
													},
													"computed": false
												},
												{
													"type": "Literal",
													"start": 1398,
													"end": 1402,
													"value": "5v",
													"raw": "'5v'"
												}
											]
										}
									}
								]
							}
						}
					},
					{
						"type": "MethodDefinition",
						"start": 1412,
						"end": 1636,
						"kind": "method",
						"static": false,
						"computed": false,
						"key": {
							"type": "Identifier",
							"start": 1412,
							"end": 1420,
							"name": "heatWait"
						},
						"value": {
							"type": "FunctionExpression",
							"start": 1420,
							"end": 1636,
							"id": null,
							"expression": false,
							"generator": false,
							"async": false,
							"params": [
								{
									"type": "Identifier",
									"start": 1421,
									"end": 1428,
									"name": "seconds"
								}
							],
							"body": {
								"type": "BlockStatement",
								"start": 1430,
								"end": 1636,
								"body": [
									{
										"type": "ExpressionStatement",
										"start": 1436,
										"end": 1456,
										"expression": {
											"type": "CallExpression",
											"start": 1436,
											"end": 1455,
											"callee": {
												"type": "MemberExpression",
												"start": 1436,
												"end": 1453,
												"object": {
													"type": "ThisExpression",
													"start": 1436,
													"end": 1440
												},
												"property": {
													"type": "Identifier",
													"start": 1441,
													"end": 1453,
													"name": "startHeating"
												},
												"computed": false
											},
											"arguments": []
										}
									},
									{
										"type": "IfStatement",
										"start": 1461,
										"end": 1552,
										"test": {
											"type": "BinaryExpression",
											"start": 1465,
											"end": 1476,
											"left": {
												"type": "Identifier",
												"start": 1465,
												"end": 1472,
												"name": "seconds"
											},
											"operator": ">",
											"right": {
												"type": "Literal",
												"start": 1475,
												"end": 1476,
												"value": 0,
												"raw": "0"
											}
										},
										"consequent": {
											"type": "BlockStatement",
											"start": 1478,
											"end": 1508,
											"body": [
												{
													"type": "ExpressionStatement",
													"start": 1486,
													"end": 1502,
													"expression": {
														"type": "AssignmentExpression",
														"start": 1486,
														"end": 1501,
														"operator": "*=",
														"left": {
															"type": "Identifier",
															"start": 1486,
															"end": 1493,
															"name": "seconds"
														},
														"right": {
															"type": "Literal",
															"start": 1497,
															"end": 1501,
															"value": 1000,
															"raw": "1000"
														}
													}
												}
											]
										},
										"alternate": {
											"type": "BlockStatement",
											"start": 1514,
											"end": 1552,
											"body": [
												{
													"type": "ExpressionStatement",
													"start": 1522,
													"end": 1546,
													"expression": {
														"type": "AssignmentExpression",
														"start": 1522,
														"end": 1545,
														"operator": "=",
														"left": {
															"type": "Identifier",
															"start": 1522,
															"end": 1529,
															"name": "seconds"
														},
														"right": {
															"type": "BinaryExpression",
															"start": 1532,
															"end": 1545,
															"left": {
																"type": "BinaryExpression",
																"start": 1532,
																"end": 1538,
																"left": {
																	"type": "Literal",
																	"start": 1532,
																	"end": 1533,
																	"value": 2,
																	"raw": "2"
																},
																"operator": "*",
																"right": {
																	"type": "Literal",
																	"start": 1536,
																	"end": 1538,
																	"value": 60,
																	"raw": "60"
																}
															},
															"operator": "*",
															"right": {
																"type": "Literal",
																"start": 1541,
																"end": 1545,
																"value": 1000,
																"raw": "1000"
															}
														}
													}
												}
											]
										}
									},
									{
										"type": "ReturnStatement",
										"start": 1557,
										"end": 1632,
										"argument": {
											"type": "NewExpression",
											"start": 1564,
											"end": 1631,
											"callee": {
												"type": "Identifier",
												"start": 1568,
												"end": 1575,
												"name": "Promise"
											},
											"arguments": [
												{
													"type": "ArrowFunctionExpression",
													"start": 1576,
													"end": 1630,
													"id": null,
													"expression": false,
													"generator": false,
													"async": false,
													"params": [
														{
															"type": "Identifier",
															"start": 1576,
															"end": 1583,
															"name": "resolve"
														}
													],
													"body": {
														"type": "BlockStatement",
														"start": 1587,
														"end": 1630,
														"body": [
															{
																"type": "ExpressionStatement",
																"start": 1595,
																"end": 1624,
																"expression": {
																	"type": "CallExpression",
																	"start": 1595,
																	"end": 1623,
																	"callee": {
																		"type": "Identifier",
																		"start": 1595,
																		"end": 1605,
																		"name": "setTimeout"
																	},
																	"arguments": [
																		{
																			"type": "Identifier",
																			"start": 1606,
																			"end": 1613,
																			"name": "resolve"
																		},
																		{
																			"type": "Identifier",
																			"start": 1615,
																			"end": 1622,
																			"name": "seconds"
																		}
																	]
																}
															}
														]
													}
												}
											]
										}
									}
								]
							}
						}
					}
				]
			}
		},
		{
			"type": "IfStatement",
			"start": 1955,
			"end": 2014,
			"test": {
				"type": "BinaryExpression",
				"start": 1959,
				"end": 1985,
				"left": {
					"type": "UnaryExpression",
					"start": 1959,
					"end": 1972,
					"operator": "typeof",
					"prefix": true,
					"argument": {
						"type": "Identifier",
						"start": 1966,
						"end": 1972,
						"name": "module"
					}
				},
				"operator": "===",
				"right": {
					"type": "Literal",
					"start": 1977,
					"end": 1985,
					"value": "object",
					"raw": "'object'"
				}
			},
			"consequent": {
				"type": "BlockStatement",
				"start": 1987,
				"end": 2014,
				"body": [
					{
						"type": "ExpressionStatement",
						"start": 1991,
						"end": 2012,
						"expression": {
							"type": "AssignmentExpression",
							"start": 1991,
							"end": 2011,
							"operator": "=",
							"left": {
								"type": "MemberExpression",
								"start": 1991,
								"end": 2005,
								"object": {
									"type": "Identifier",
									"start": 1991,
									"end": 1997,
									"name": "module"
								},
								"property": {
									"type": "Identifier",
									"start": 1998,
									"end": 2005,
									"name": "exports"
								},
								"computed": false
							},
							"right": {
								"type": "Identifier",
								"start": 2008,
								"end": 2011,
								"name": "MQ5"
							}
						}
					}
				]
			},
			"alternate": null
		}
	],
	"sourceType": "script"
}